asana_cli/__init__.py
asana_cli/cli.py
asana_cli/version.py
asana_cli_acpepper-0.0.3.dist-info/LICENSE
asana_cli_acpepper-0.0.3.dist-info/METADATA
asana_cli_acpepper-0.0.3.dist-info/WHEEL
asana_cli_acpepper-0.0.3.dist-info/entry_points.txt
asana_cli_acpepper-0.0.3.dist-info/top_level.txt
asana_cli_acpepper-0.0.3.dist-info/RECORD
