Metadata-Version: 2.1
Name: asana-cli-acpepper
Version: 0.0.3
Summary: CLI for asana.
Home-page: https://github.com/AlJohri/asana-cli
Author: Al Johri
Author-email: al.johri@gmail.com
Maintainer: Andrew Pepper
Maintainer-email: andrewpepper96@gmail.com
License: MIT
Platform: UNKNOWN
Classifier: Programming Language :: Python :: 3 :: Only
Classifier: Programming Language :: Python :: 3.6
Classifier: License :: OSI Approved :: MIT License
License-File: LICENSE
Requires-Dist: click
Requires-Dist: asana
